constructpy/__init__.py
constructpy/__main__.py
constructpy/constructpy.py
constructpy/worldcities.csv
constructpy-0.0.8.dist-info/LICENSE
constructpy-0.0.8.dist-info/METADATA
constructpy-0.0.8.dist-info/WHEEL
constructpy-0.0.8.dist-info/entry_points.txt
constructpy-0.0.8.dist-info/top_level.txt
constructpy-0.0.8.dist-info/RECORD
